setup.py
client/__init__.py
client/add_contact.py
client/database.py
client/del_contact.py
client/main_window.py
client/main_window_conv.py
client/start_dialog.py
client/transport.py
common/__init__.py
common/answers.py
common/decorators.py
common/descryptors.py
common/errors.py
common/metaclasses.py
common/utils.py
log/__init__.py
log/client_log_config.py
log/server_log_config.py
samoryad_messenger_client.egg-info/PKG-INFO
samoryad_messenger_client.egg-info/SOURCES.txt
samoryad_messenger_client.egg-info/dependency_links.txt
samoryad_messenger_client.egg-info/requires.txt
samoryad_messenger_client.egg-info/top_level.txt