Metadata-Version: 1.0
Name: samoryad-messenger-client
Version: 0.0.2
Summary: mess_client
Home-page: UNKNOWN
Author: Andrey Samoryadov
Author-email: samoryadov@yandex.ru
License: UNKNOWN
Platform: UNKNOWN
